gdjd2l/__init__.py
gdjd2l/torch.py
gdjd2l-0.1.1.dist-info/LICENSE
gdjd2l-0.1.1.dist-info/METADATA
gdjd2l-0.1.1.dist-info/WHEEL
gdjd2l-0.1.1.dist-info/top_level.txt
gdjd2l-0.1.1.dist-info/RECORD
