Metadata-Version: 2.1
Name: gdjd2l
Version: 0.1.1
Summary: use for deep to learn
Author: Goodongj
Author-email: 
License-File: LICENSE
Requires-Dist: torch >=2.3.1
Requires-Dist: numpy
Requires-Dist: pandas
